{
  "verse_key": "19:42",
  "timestamp_from": 487610,
  "timestamp_to": 498940,
  "duration": 11330,
  "segments": [
    [
      1,
      487910,
      488320
    ],
    [
      2,
      488320,
      488940
    ],
    [
      3,
      488940,
      489980
    ],
    [
      4,
      489980,
      490360
    ],
    [
      5,
      490360,
      490960
    ],
    [
      6,
      490960,
      491340
    ],
    [
      7,
      491340,
      492170
    ],
    [
      8,
      492170,
      492580
    ],
    [
      9,
      492580,
      492990
    ],
    [
      10,
      492990,
      493750
    ],
    [
      11,
      493750,
      494350
    ],
    [
      12,
      494350,
      495140
    ],
    [
      13,
      495140,
      495740
    ],
    [
      14,
      495740,
      496570
    ],
    [
      15,
      496570,
      497620
    ]
  ]
}