{
  "verse_key": "19:74",
  "timestamp_from": 903050,
  "timestamp_to": 912720,
  "duration": 9670,
  "segments": [
    [
      1,
      903350,
      903940
    ],
    [
      2,
      903940,
      905140
    ],
    [
      3,
      905140,
      906750
    ],
    [
      4,
      906750,
      907940
    ],
    [
      5,
      907940,
      908740
    ],
    [
      6,
      908740,
      909160
    ],
    [
      7,
      909160,
      909930
    ],
    [
      8,
      909930,
      911610
    ],
    [
      9,
      911610,
      912720
    ]
  ]
}