{
  "verse_key": "39:32",
  "timestamp_from": 634790,
  "timestamp_to": 652010,
  "duration": 17220,
  "segments": [
    [
      1,
      634990,
      635590
    ],
    [
      2,
      635590,
      636380
    ],
    [
      3,
      636380,
      638635
    ],
    [
      4,
      638635,
      639260
    ],
    [
      5,
      639260,
      639700
    ],
    [
      6,
      639800,
      640450
    ],
    [
      7,
      640450,
      641450
    ],
    [
      8,
      641450,
      642460
    ],
    [
      9,
      642460,
      642890
    ],
    [
      10,
      642890,
      645430
    ],
    [
      11,
      645430,
      646200
    ],
    [
      12,
      646200,
      646590
    ],
    [
      13,
      646590,
      648415
    ],
    [
      14,
      648415,
      649030
    ],
    [
      15,
      649170,
      652010
    ]
  ]
}