{
  "verse_key": "39:23",
  "timestamp_from": 493450,
  "timestamp_to": 530420,
  "duration": 36970,
  "segments": [
    [
      1,
      493750,
      494410
    ],
    [
      2,
      494410,
      495200
    ],
    [
      3,
      495200,
      496010
    ],
    [
      4,
      496010,
      496960
    ],
    [
      5,
      496960,
      498580
    ],
    [
      6,
      498580,
      500520
    ],
    [
      7,
      500520,
      502270
    ],
    [
      7,
      502270,
      503230
    ],
    [
      8,
      503230,
      504470
    ],
    [
      9,
      504470,
      505050
    ],
    [
      10,
      505050,
      505920
    ],
    [
      11,
      506000,
      506900
    ],
    [
      12,
      506900,
      507890
    ],
    [
      13,
      507890,
      508880
    ],
    [
      14,
      508880,
      510460
    ],
    [
      15,
      510460,
      511080
    ],
    [
      16,
      511080,
      512510
    ],
    [
      17,
      512510,
      513970
    ],
    [
      18,
      513970,
      514560
    ],
    [
      19,
      514560,
      515170
    ],
    [
      20,
      515270,
      517510
    ],
    [
      21,
      517510,
      518190
    ],
    [
      22,
      518270,
      518730
    ],
    [
      23,
      518850,
      519490
    ],
    [
      24,
      519490,
      520070
    ],
    [
      25,
      520250,
      520870
    ],
    [
      26,
      520870,
      521960
    ],
    [
      27,
      521960,
      524290
    ],
    [
      28,
      524290,
      525460
    ],
    [
      29,
      525460,
      526100
    ],
    [
      30,
      526380,
      527010
    ],
    [
      31,
      527010,
      527630
    ],
    [
      32,
      527630,
      528250
    ],
    [
      33,
      528250,
      528600
    ],
    [
      34,
      528620,
      530420
    ]
  ]
}