{
  "verse_key": "21:108",
  "timestamp_from": 1460310,
  "timestamp_to": 1476250,
  "duration": 15940,
  "segments": [
    [
      1,
      1460310,
      1460720
    ],
    [
      2,
      1460720,
      1462680
    ],
    [
      3,
      1462680,
      1463550
    ],
    [
      4,
      1463550,
      1464370
    ],
    [
      5,
      1464370,
      1466230
    ],
    [
      6,
      1466230,
      1467480
    ],
    [
      7,
      1467480,
      1469410
    ],
    [
      8,
      1469410,
      1470970
    ],
    [
      9,
      1470970,
      1471580
    ],
    [
      10,
      1471580,
      1473810
    ],
    [
      11,
      1473810,
      1476250
    ]
  ]
}