{
  "verse_key": "76:9",
  "timestamp_from": 90440,
  "timestamp_to": 102650,
  "duration": 12210,
  "segments": [
    [
      1,
      90640,
      92560
    ],
    [
      2,
      92560,
      93790
    ],
    [
      3,
      93790,
      94620
    ],
    [
      4,
      94700,
      95430
    ],
    [
      5,
      95430,
      95840
    ],
    [
      6,
      95840,
      96660
    ],
    [
      7,
      96660,
      98130
    ],
    [
      8,
      98130,
      100970
    ],
    [
      9,
      100970,
      101560
    ],
    [
      10,
      101560,
      102650
    ]
  ]
}