{
  "verse_key": "59:3",
  "timestamp_from": 61220,
  "timestamp_to": 77340,
  "duration": 16120,
  "segments": [
    [
      1,
      61420,
      62440
    ],
    [
      2,
      62440,
      63550
    ],
    [
      3,
      63550,
      64210
    ],
    [
      4,
      64290,
      64950
    ],
    [
      5,
      64950,
      65970
    ],
    [
      6,
      65970,
      68220
    ],
    [
      7,
      68220,
      69550
    ],
    [
      8,
      69550,
      69770
    ],
    [
      9,
      69770,
      71520
    ],
    [
      10,
      71520,
      72300
    ],
    [
      11,
      72300,
      72540
    ],
    [
      12,
      72560,
      73660
    ],
    [
      13,
      73660,
      75490
    ],
    [
      14,
      75490,
      77340
    ]
  ]
}