{
  "verse_key": "3:188",
  "timestamp_from": 3917390,
  "timestamp_to": 3940110,
  "duration": 22720,
  "segments": [
    [
      1,
      3917590,
      3918010
    ],
    [
      2,
      3918010,
      3919830
    ],
    [
      3,
      3919930,
      3920740
    ],
    [
      4,
      3920740,
      3921890
    ],
    [
      5,
      3921890,
      3922450
    ],
    [
      6,
      3922450,
      3923090
    ],
    [
      7,
      3923090,
      3924390
    ],
    [
      8,
      3924390,
      3925390
    ],
    [
      9,
      3925390,
      3926310
    ],
    [
      10,
      3926310,
      3926930
    ],
    [
      11,
      3926930,
      3927320
    ],
    [
      12,
      3927320,
      3928200
    ],
    [
      13,
      3928200,
      3928790
    ],
    [
      14,
      3928790,
      3931650
    ],
    [
      15,
      3931650,
      3933440
    ],
    [
      16,
      3933440,
      3933820
    ],
    [
      17,
      3933840,
      3936355
    ],
    [
      18,
      3936355,
      3937120
    ],
    [
      19,
      3937120,
      3938080
    ],
    [
      20,
      3938080,
      3940010
    ]
  ]
}