{
  "verse_key": "38:25",
  "timestamp_from": 313710,
  "timestamp_to": 324340,
  "duration": 10630,
  "segments": [
    [
      1,
      313910,
      315160
    ],
    [
      2,
      315160,
      315770
    ],
    [
      3,
      315770,
      316510
    ],
    [
      4,
      316610,
      318100
    ],
    [
      5,
      318100,
      318720
    ],
    [
      6,
      318720,
      320390
    ],
    [
      7,
      320390,
      321420
    ],
    [
      8,
      321420,
      322130
    ],
    [
      9,
      322210,
      324340
    ]
  ]
}