{
  "verse_key": "15:15",
  "timestamp_from": 135880,
  "timestamp_to": 145830,
  "duration": 9950,
  "segments": [
    [
      1,
      136080,
      137140
    ],
    [
      2,
      137140,
      138650
    ],
    [
      3,
      138650,
      139620
    ],
    [
      4,
      139620,
      140990
    ],
    [
      5,
      140990,
      141390
    ],
    [
      6,
      141390,
      141970
    ],
    [
      7,
      141970,
      143260
    ],
    [
      8,
      143260,
      145830
    ]
  ]
}