{
  "verse_key": "6:95",
  "timestamp_from": 1923240,
  "timestamp_to": 1942820,
  "duration": 19580,
  "segments": [
    [
      1,
      1923440,
      1925240
    ],
    [
      2,
      1925380,
      1926050
    ],
    [
      3,
      1926050,
      1926940
    ],
    [
      4,
      1926940,
      1927710
    ],
    [
      5,
      1927710,
      1930380
    ],
    [
      6,
      1930380,
      1931170
    ],
    [
      7,
      1931170,
      1931960
    ],
    [
      8,
      1931960,
      1932370
    ],
    [
      9,
      1932390,
      1933340
    ],
    [
      10,
      1933340,
      1934310
    ],
    [
      11,
      1934330,
      1935280
    ],
    [
      12,
      1935280,
      1935690
    ],
    [
      13,
      1935730,
      1936890
    ],
    [
      14,
      1936890,
      1937930
    ],
    [
      15,
      1938030,
      1938710
    ],
    [
      16,
      1938710,
      1940510
    ],
    [
      17,
      1940510,
      1942820
    ]
  ]
}