{
  "verse_key": "8:24",
  "timestamp_from": 420230,
  "timestamp_to": 442210,
  "duration": 21980,
  "segments": [
    [
      1,
      420230,
      420640
    ],
    [
      2,
      420640,
      421430
    ],
    [
      3,
      421510,
      422340
    ],
    [
      4,
      422340,
      423130
    ],
    [
      5,
      423130,
      424350
    ],
    [
      6,
      424350,
      425300
    ],
    [
      7,
      425300,
      426700
    ],
    [
      8,
      426700,
      427310
    ],
    [
      9,
      427310,
      428320
    ],
    [
      10,
      428320,
      428900
    ],
    [
      11,
      428900,
      430840
    ],
    [
      12,
      430840,
      431790
    ],
    [
      13,
      431790,
      433120
    ],
    [
      14,
      433200,
      433890
    ],
    [
      15,
      433890,
      434750
    ],
    [
      16,
      434750,
      435340
    ],
    [
      17,
      435380,
      436120
    ],
    [
      18,
      436120,
      437330
    ],
    [
      19,
      437330,
      438960
    ],
    [
      20,
      438960,
      439760
    ]
  ]
}