{
  "verse_key": "20:22",
  "timestamp_from": 168910,
  "timestamp_to": 181100,
  "duration": 12190,
  "segments": [
    [
      1,
      169210,
      170090
    ],
    [
      2,
      170090,
      170590
    ],
    [
      3,
      170670,
      171310
    ],
    [
      4,
      171310,
      172260
    ],
    [
      5,
      172360,
      173190
    ],
    [
      6,
      173190,
      175630
    ],
    [
      7,
      175630,
      176020
    ],
    [
      8,
      176020,
      176650
    ],
    [
      9,
      176650,
      178790
    ],
    [
      10,
      178790,
      179830
    ],
    [
      11,
      179830,
      181100
    ]
  ]
}