{
  "verse_key": "16:70",
  "timestamp_from": 1154730,
  "timestamp_to": 1178490,
  "duration": 23760,
  "segments": [
    [
      1,
      1154930,
      1155950
    ],
    [
      2,
      1155950,
      1156990
    ],
    [
      3,
      1156990,
      1158470
    ],
    [
      4,
      1158470,
      1160800
    ],
    [
      5,
      1160800,
      1163050
    ],
    [
      6,
      1163050,
      1163980
    ],
    [
      7,
      1163980,
      1164720
    ],
    [
      8,
      1164720,
      1165320
    ],
    [
      9,
      1165320,
      1166110
    ],
    [
      10,
      1166110,
      1166890
    ],
    [
      11,
      1166890,
      1167530
    ],
    [
      12,
      1167530,
      1167920
    ],
    [
      13,
      1167920,
      1168740
    ],
    [
      14,
      1168740,
      1169320
    ],
    [
      15,
      1169320,
      1170940
    ],
    [
      16,
      1170940,
      1172530
    ],
    [
      17,
      1172530,
      1173870
    ],
    [
      18,
      1173990,
      1174660
    ],
    [
      19,
      1174660,
      1176610
    ],
    [
      20,
      1176610,
      1178490
    ]
  ]
}