{
  "verse_key": "16:44",
  "timestamp_from": 704830,
  "timestamp_to": 721630,
  "duration": 16800,
  "segments": [
    [
      1,
      705030,
      706730
    ],
    [
      2,
      706730,
      708400
    ],
    [
      3,
      708400,
      710670
    ],
    [
      4,
      710670,
      711360
    ],
    [
      5,
      711400,
      712230
    ],
    [
      6,
      712230,
      713450
    ],
    [
      7,
      713450,
      715150
    ],
    [
      8,
      715150,
      715540
    ],
    [
      9,
      715540,
      716320
    ],
    [
      10,
      716320,
      717400
    ],
    [
      11,
      717400,
      718790
    ],
    [
      12,
      718790,
      721630
    ]
  ]
}