{
  "verse_key": "18:44",
  "timestamp_from": 895770,
  "timestamp_to": 906860,
  "duration": 11090,
  "segments": [
    [
      1,
      896070,
      897010
    ],
    [
      2,
      897170,
      898250
    ],
    [
      3,
      898350,
      899410
    ],
    [
      4,
      899450,
      901180
    ],
    [
      5,
      901180,
      901590
    ],
    [
      6,
      901590,
      902990
    ],
    [
      7,
      902990,
      904630
    ],
    [
      8,
      904630,
      905660
    ],
    [
      9,
      905660,
      906860
    ]
  ]
}