{
  "verse_key": "5:60",
  "timestamp_from": 1798740,
  "timestamp_to": 1832850,
  "duration": 34110,
  "segments": [
    [
      1,
      1798940,
      1799290
    ],
    [
      2,
      1799290,
      1799710
    ],
    [
      3,
      1799710,
      1801710
    ],
    [
      4,
      1801710,
      1803410
    ],
    [
      5,
      1803410,
      1804510
    ],
    [
      6,
      1804510,
      1805230
    ],
    [
      7,
      1805310,
      1806570
    ],
    [
      8,
      1806570,
      1807790
    ],
    [
      9,
      1807890,
      1810280
    ],
    [
      10,
      1810280,
      1810650
    ],
    [
      11,
      1810650,
      1811470
    ],
    [
      12,
      1811570,
      1812240
    ],
    [
      13,
      1812240,
      1812990
    ],
    [
      14,
      1812990,
      1813810
    ],
    [
      15,
      1813810,
      1814590
    ],
    [
      16,
      1814590,
      1815360
    ],
    [
      17,
      1815360,
      1816370
    ],
    [
      18,
      1816370,
      1817970
    ],
    [
      19,
      1817970,
      1818780
    ],
    [
      20,
      1818780,
      1821710
    ],
    [
      21,
      1821710,
      1823890
    ],
    [
      22,
      1823990,
      1825380
    ],
    [
      23,
      1825380,
      1827150
    ],
    [
      24,
      1827150,
      1828110
    ],
    [
      25,
      1828110,
      1829020
    ],
    [
      26,
      1829020,
      1830790
    ],
    [
      27,
      1830790,
      1832850
    ]
  ]
}