{
  "verse_key": "4:1",
  "timestamp_from": 5050,
  "timestamp_to": 44380,
  "duration": 39330,
  "segments": [
    [
      1,
      5250,
      5690
    ],
    [
      2,
      5690,
      6530
    ],
    [
      3,
      7510,
      8190
    ],
    [
      4,
      8190,
      9010
    ],
    [
      5,
      9010,
      9990
    ],
    [
      6,
      10050,
      10710
    ],
    [
      7,
      10710,
      12240
    ],
    [
      8,
      12240,
      13100
    ],
    [
      9,
      13100,
      14420
    ],
    [
      10,
      14420,
      16170
    ],
    [
      11,
      16170,
      16990
    ],
    [
      12,
      16990,
      17790
    ],
    [
      13,
      17790,
      19800
    ],
    [
      11,
      19800,
      20590
    ],
    [
      12,
      20590,
      21340
    ],
    [
      13,
      21340,
      21620
    ],
    [
      14,
      21740,
      22400
    ],
    [
      15,
      22400,
      23190
    ],
    [
      16,
      23190,
      24170
    ],
    [
      17,
      24170,
      25640
    ],
    [
      18,
      25640,
      27520
    ],
    [
      19,
      27520,
      30880
    ],
    [
      20,
      30880,
      31670
    ],
    [
      21,
      31770,
      32450
    ],
    [
      22,
      32530,
      33250
    ],
    [
      23,
      33250,
      35510
    ],
    [
      24,
      35510,
      36130
    ],
    [
      25,
      36130,
      39410
    ],
    [
      26,
      39410,
      40800
    ],
    [
      27,
      40920,
      41600
    ],
    [
      28,
      41600,
      42220
    ]
  ]
}