{
  "verse_key": "4:159",
  "timestamp_from": 3946450,
  "timestamp_to": 3959840,
  "duration": 13390,
  "segments": [
    [
      1,
      3946650,
      3948200
    ],
    [
      2,
      3948200,
      3948560
    ],
    [
      3,
      3948560,
      3949130
    ],
    [
      4,
      3949130,
      3950080
    ],
    [
      5,
      3950080,
      3950860
    ],
    [
      6,
      3950860,
      3952890
    ],
    [
      7,
      3952890,
      3953490
    ],
    [
      8,
      3953490,
      3954070
    ],
    [
      9,
      3954070,
      3955070
    ],
    [
      10,
      3955070,
      3955840
    ],
    [
      11,
      3955840,
      3956980
    ],
    [
      12,
      3956980,
      3957790
    ],
    [
      13,
      3957790,
      3958780
    ],
    [
      14,
      3958780,
      3959640
    ]
  ]
}