{
  "verse_key": "4:41",
  "timestamp_from": 1205730,
  "timestamp_to": 1219020,
  "duration": 13290,
  "segments": [
    [
      1,
      1205930,
      1206720
    ],
    [
      2,
      1206720,
      1207330
    ],
    [
      3,
      1207330,
      1208160
    ],
    [
      4,
      1208160,
      1209160
    ],
    [
      5,
      1209160,
      1209740
    ],
    [
      6,
      1209740,
      1211850
    ],
    [
      7,
      1211850,
      1213580
    ],
    [
      8,
      1213580,
      1214470
    ],
    [
      9,
      1214470,
      1214780
    ],
    [
      10,
      1214860,
      1215460
    ],
    [
      11,
      1215460,
      1217850
    ],
    [
      12,
      1217850,
      1219020
    ]
  ]
}