{
  "verse_key": "4:162",
  "timestamp_from": 3990210,
  "timestamp_to": 4020840,
  "duration": 30630,
  "segments": [
    [
      1,
      3990510,
      3991330
    ],
    [
      2,
      3991390,
      3992670
    ],
    [
      3,
      3992670,
      3992920
    ],
    [
      4,
      3992920,
      3993620
    ],
    [
      5,
      3993620,
      3994380
    ],
    [
      6,
      3994380,
      3995930
    ],
    [
      7,
      3995930,
      3997070
    ],
    [
      8,
      3997070,
      3997670
    ],
    [
      9,
      3997670,
      3999050
    ],
    [
      10,
      3999050,
      3999740
    ],
    [
      11,
      3999840,
      4000420
    ],
    [
      12,
      4000420,
      4002050
    ],
    [
      13,
      4002050,
      4003030
    ],
    [
      14,
      4003030,
      4004520
    ],
    [
      15,
      4004520,
      4006050
    ],
    [
      16,
      4006050,
      4008680
    ],
    [
      17,
      4008680,
      4009970
    ],
    [
      18,
      4009970,
      4011030
    ],
    [
      19,
      4011030,
      4012510
    ],
    [
      20,
      4012510,
      4013500
    ],
    [
      21,
      4013500,
      4014490
    ],
    [
      22,
      4014510,
      4015450
    ],
    [
      23,
      4015450,
      4017440
    ],
    [
      24,
      4017520,
      4018950
    ],
    [
      25,
      4018950,
      4019840
    ],
    [
      26,
      4019840,
      4020840
    ]
  ]
}