{
  "verse_key": "11:35",
  "timestamp_from": 756360,
  "timestamp_to": 773100,
  "duration": 16740,
  "segments": [
    [
      1,
      756560,
      757000
    ],
    [
      2,
      757000,
      758260
    ],
    [
      3,
      758260,
      760820
    ],
    [
      4,
      760820,
      761220
    ],
    [
      5,
      761220,
      761590
    ],
    [
      6,
      761590,
      763060
    ],
    [
      7,
      763060,
      764140
    ],
    [
      8,
      764140,
      765460
    ],
    [
      9,
      765460,
      766060
    ],
    [
      10,
      766060,
      769080
    ],
    [
      11,
      769080,
      770720
    ],
    [
      12,
      770720,
      773100
    ]
  ]
}