{
  "verse_key": "11:84",
  "timestamp_from": 1722280,
  "timestamp_to": 1754950,
  "duration": 32670,
  "segments": [
    [
      1,
      1722480,
      1723320
    ],
    [
      2,
      1723320,
      1724110
    ],
    [
      3,
      1724110,
      1725170
    ],
    [
      4,
      1725170,
      1727150
    ],
    [
      5,
      1727150,
      1727760
    ],
    [
      6,
      1727760,
      1728170
    ],
    [
      7,
      1728170,
      1728760
    ],
    [
      8,
      1728760,
      1729460
    ],
    [
      9,
      1729520,
      1730210
    ],
    [
      10,
      1730210,
      1730630
    ],
    [
      11,
      1730630,
      1732000
    ],
    [
      12,
      1732000,
      1732380
    ],
    [
      13,
      1732380,
      1733410
    ],
    [
      14,
      1733410,
      1734970
    ],
    [
      15,
      1734970,
      1735580
    ],
    [
      16,
      1735580,
      1737120
    ],
    [
      17,
      1737120,
      1738340
    ],
    [
      18,
      1738340,
      1741710
    ],
    [
      19,
      1741710,
      1743510
    ],
    [
      20,
      1743510,
      1745140
    ],
    [
      21,
      1745140,
      1746890
    ],
    [
      22,
      1746890,
      1748620
    ],
    [
      23,
      1748620,
      1749520
    ],
    [
      24,
      1749520,
      1750590
    ],
    [
      25,
      1750590,
      1751440
    ],
    [
      26,
      1751440,
      1753020
    ]
  ]
}