{
  "verse_key": "11:85",
  "timestamp_from": 1755350,
  "timestamp_to": 1771630,
  "duration": 16280,
  "segments": [
    [
      1,
      1755550,
      1756170
    ],
    [
      2,
      1756170,
      1756780
    ],
    [
      3,
      1756780,
      1757470
    ],
    [
      4,
      1757470,
      1758690
    ],
    [
      5,
      1758690,
      1760140
    ],
    [
      6,
      1760140,
      1761190
    ],
    [
      7,
      1761190,
      1761790
    ],
    [
      8,
      1761790,
      1762700
    ],
    [
      9,
      1763380,
      1764100
    ],
    [
      10,
      1764100,
      1766700
    ],
    [
      11,
      1766700,
      1767330
    ],
    [
      12,
      1767330,
      1768140
    ],
    [
      13,
      1768140,
      1768400
    ],
    [
      14,
      1768420,
      1769150
    ]
  ]
}