{
  "verse_key": "28:32",
  "timestamp_from": 648260,
  "timestamp_to": 675820,
  "duration": 27560,
  "segments": [
    [
      1,
      648460,
      649300
    ],
    [
      2,
      649300,
      649780
    ],
    [
      3,
      649860,
      650280
    ],
    [
      4,
      650280,
      651000
    ],
    [
      5,
      651080,
      651910
    ],
    [
      6,
      651910,
      653990
    ],
    [
      7,
      653990,
      654350
    ],
    [
      8,
      654350,
      654940
    ],
    [
      9,
      654940,
      657400
    ],
    [
      10,
      657400,
      658220
    ],
    [
      11,
      658220,
      658890
    ],
    [
      12,
      658990,
      660030
    ],
    [
      13,
      660030,
      660430
    ],
    [
      14,
      660550,
      662080
    ],
    [
      15,
      662080,
      663010
    ],
    [
      16,
      663090,
      664520
    ],
    [
      17,
      664520,
      664730
    ],
    [
      18,
      664830,
      665590
    ],
    [
      19,
      665650,
      666250
    ],
    [
      20,
      666250,
      667310
    ],
    [
      21,
      667310,
      669120
    ],
    [
      22,
      669120,
      670910
    ],
    [
      23,
      670910,
      671770
    ],
    [
      24,
      671770,
      673360
    ],
    [
      25,
      673360,
      675820
    ]
  ]
}