{
  "verse_key": "28:22",
  "timestamp_from": 407030,
  "timestamp_to": 422190,
  "duration": 15160,
  "segments": [
    [
      1,
      407230,
      409080
    ],
    [
      2,
      409080,
      410130
    ],
    [
      3,
      410130,
      412560
    ],
    [
      4,
      412560,
      413370
    ],
    [
      5,
      413370,
      413990
    ],
    [
      6,
      413990,
      414650
    ],
    [
      7,
      414650,
      415430
    ],
    [
      8,
      415430,
      416600
    ],
    [
      9,
      416600,
      417810
    ],
    [
      10,
      417810,
      419830
    ],
    [
      11,
      419830,
      422190
    ]
  ]
}