{
  "verse_key": "43:15",
  "timestamp_from": 171100,
  "timestamp_to": 184230,
  "duration": 13130,
  "segments": [
    [
      1,
      171300,
      172400
    ],
    [
      2,
      172400,
      173020
    ],
    [
      3,
      173020,
      173450
    ],
    [
      4,
      173450,
      174780
    ],
    [
      5,
      174780,
      176460
    ],
    [
      6,
      176460,
      177940
    ],
    [
      7,
      178020,
      179970
    ],
    [
      8,
      180110,
      182150
    ],
    [
      9,
      182150,
      184230
    ]
  ]
}