{
  "verse_key": "7:62",
  "timestamp_from": 1312760,
  "timestamp_to": 1324090,
  "duration": 11330,
  "segments": [
    [
      1,
      1312960,
      1314370
    ],
    [
      2,
      1314370,
      1315620
    ],
    [
      3,
      1315620,
      1316410
    ],
    [
      4,
      1316410,
      1318020
    ],
    [
      5,
      1318120,
      1318730
    ],
    [
      6,
      1318730,
      1319670
    ],
    [
      7,
      1319670,
      1320060
    ],
    [
      8,
      1320220,
      1320900
    ],
    [
      9,
      1320900,
      1321320
    ],
    [
      10,
      1321320,
      1321720
    ],
    [
      11,
      1321720,
      1324090
    ]
  ]
}