{
  "verse_key": "7:169",
  "timestamp_from": 3496470,
  "timestamp_to": 3546300,
  "duration": 49830,
  "segments": [
    [
      1,
      3496670,
      3497510
    ],
    [
      2,
      3497510,
      3498520
    ],
    [
      3,
      3498520,
      3499500
    ],
    [
      4,
      3499500,
      3500980
    ],
    [
      5,
      3500980,
      3501570
    ],
    [
      6,
      3501570,
      3502580
    ],
    [
      7,
      3502580,
      3503730
    ],
    [
      8,
      3503730,
      3504370
    ],
    [
      9,
      3504370,
      3505060
    ],
    [
      10,
      3505120,
      3506030
    ],
    [
      11,
      3506030,
      3507480
    ],
    [
      12,
      3507480,
      3508480
    ],
    [
      13,
      3508480,
      3510040
    ],
    [
      11,
      3510040,
      3511470
    ],
    [
      12,
      3511470,
      3512470
    ],
    [
      13,
      3512470,
      3513110
    ],
    [
      14,
      3513110,
      3514650
    ],
    [
      15,
      3514650,
      3515610
    ],
    [
      16,
      3515610,
      3517120
    ],
    [
      17,
      3517120,
      3518100
    ],
    [
      18,
      3518100,
      3521720
    ],
    [
      19,
      3521720,
      3522340
    ],
    [
      20,
      3522340,
      3523130
    ],
    [
      21,
      3523130,
      3524920
    ],
    [
      22,
      3524920,
      3525980
    ],
    [
      23,
      3525980,
      3526960
    ],
    [
      24,
      3526960,
      3527040
    ],
    [
      25,
      3527340,
      3527760
    ],
    [
      26,
      3527760,
      3528870
    ],
    [
      27,
      3528870,
      3529300
    ],
    [
      28,
      3529380,
      3530070
    ],
    [
      29,
      3530070,
      3530700
    ],
    [
      30,
      3530700,
      3531500
    ],
    [
      31,
      3531500,
      3532420
    ],
    [
      32,
      3532540,
      3532970
    ],
    [
      33,
      3532970,
      3535350
    ],
    [
      34,
      3535350,
      3536540
    ],
    [
      35,
      3536540,
      3537540
    ],
    [
      36,
      3537540,
      3538230
    ],
    [
      37,
      3538350,
      3539540
    ],
    [
      38,
      3539540,
      3542810
    ],
    [
      39,
      3542810,
      3543670
    ],
    [
      40,
      3543670,
      3546300
    ]
  ]
}