{
  "verse_key": "7:29",
  "timestamp_from": 493640,
  "timestamp_to": 513640,
  "duration": 20000,
  "segments": [
    [
      1,
      493840,
      494250
    ],
    [
      2,
      494250,
      494890
    ],
    [
      3,
      494890,
      495730
    ],
    [
      4,
      495730,
      497570
    ],
    [
      5,
      497570,
      498860
    ],
    [
      6,
      498860,
      500170
    ],
    [
      7,
      500170,
      501390
    ],
    [
      8,
      501390,
      501790
    ],
    [
      9,
      501790,
      503720
    ],
    [
      10,
      503720,
      504760
    ],
    [
      11,
      504760,
      506000
    ],
    [
      12,
      506000,
      506430
    ],
    [
      13,
      506430,
      509110
    ],
    [
      14,
      509110,
      509710
    ],
    [
      15,
      509710,
      510730
    ],
    [
      16,
      510730,
      513640
    ]
  ]
}