{
  "verse_key": "7:76",
  "timestamp_from": 1632480,
  "timestamp_to": 1643970,
  "duration": 11490,
  "segments": [
    [
      1,
      1632680,
      1633360
    ],
    [
      2,
      1633440,
      1634300
    ],
    [
      3,
      1634300,
      1635550
    ],
    [
      4,
      1635550,
      1637250
    ],
    [
      5,
      1637250,
      1638290
    ],
    [
      6,
      1638290,
      1640910
    ],
    [
      7,
      1640910,
      1641540
    ],
    [
      8,
      1641540,
      1643970
    ]
  ]
}