{
  "verse_key": "7:147",
  "timestamp_from": 2901910,
  "timestamp_to": 2918610,
  "duration": 16700,
  "segments": [
    [
      1,
      2902110,
      2903280
    ],
    [
      2,
      2903280,
      2904300
    ],
    [
      3,
      2904300,
      2905960
    ],
    [
      4,
      2905960,
      2908320
    ],
    [
      5,
      2908340,
      2909450
    ],
    [
      6,
      2909450,
      2910240
    ],
    [
      7,
      2910240,
      2912450
    ],
    [
      8,
      2912450,
      2912890
    ],
    [
      9,
      2912890,
      2913910
    ],
    [
      10,
      2913910,
      2914770
    ],
    [
      11,
      2914770,
      2915170
    ],
    [
      12,
      2915170,
      2916060
    ],
    [
      13,
      2916060,
      2918610
    ]
  ]
}