{
  "verse_key": "7:205",
  "timestamp_from": 4197390,
  "timestamp_to": 4221840,
  "duration": 24450,
  "segments": [
    [
      1,
      4197590,
      4198430
    ],
    [
      2,
      4198430,
      4199130
    ],
    [
      3,
      4199230,
      4199490
    ],
    [
      4,
      4199610,
      4200330
    ],
    [
      5,
      4200410,
      4202310
    ],
    [
      6,
      4202310,
      4204110
    ],
    [
      7,
      4204110,
      4204900
    ],
    [
      8,
      4204960,
      4205690
    ],
    [
      9,
      4205690,
      4206080
    ],
    [
      10,
      4206080,
      4206890
    ],
    [
      11,
      4206890,
      4208110
    ],
    [
      12,
      4208110,
      4211300
    ],
    [
      7,
      4211300,
      4212110
    ],
    [
      8,
      4212130,
      4212920
    ],
    [
      9,
      4212920,
      4213290
    ],
    [
      10,
      4213290,
      4214110
    ],
    [
      11,
      4214110,
      4215320
    ],
    [
      12,
      4215320,
      4216760
    ],
    [
      13,
      4216760,
      4217350
    ],
    [
      14,
      4217350,
      4218780
    ],
    [
      15,
      4218780,
      4219150
    ],
    [
      16,
      4219150,
      4221840
    ]
  ]
}