{
  "verse_key": "24:4",
  "timestamp_from": 73920,
  "timestamp_to": 98720,
  "duration": 24800,
  "segments": [
    [
      1,
      74120,
      75270
    ],
    [
      2,
      75270,
      76320
    ],
    [
      3,
      76340,
      77720
    ],
    [
      4,
      77720,
      79270
    ],
    [
      5,
      79270,
      79690
    ],
    [
      6,
      79690,
      80460
    ],
    [
      7,
      80460,
      81610
    ],
    [
      8,
      81610,
      83810
    ],
    [
      9,
      83810,
      85180
    ],
    [
      10,
      85180,
      86410
    ],
    [
      11,
      86410,
      88120
    ],
    [
      12,
      88120,
      88700
    ],
    [
      13,
      88700,
      89730
    ],
    [
      14,
      89730,
      90320
    ],
    [
      15,
      90320,
      91580
    ],
    [
      16,
      91580,
      93400
    ],
    [
      17,
      93400,
      95540
    ],
    [
      18,
      95620,
      96070
    ],
    [
      19,
      96070,
      98720
    ]
  ]
}