{
  "verse_key": "50:27",
  "timestamp_from": 283280,
  "timestamp_to": 294930,
  "duration": 11650,
  "segments": [
    [
      1,
      283480,
      284110
    ],
    [
      2,
      284110,
      285350
    ],
    [
      3,
      285350,
      286340
    ],
    [
      4,
      286340,
      286730
    ],
    [
      5,
      286730,
      288240
    ],
    [
      6,
      288240,
      289960
    ],
    [
      7,
      289960,
      290590
    ],
    [
      8,
      290590,
      291010
    ],
    [
      9,
      291010,
      292590
    ],
    [
      10,
      292590,
      294930
    ]
  ]
}