{
  "verse_key": "35:39",
  "timestamp_from": 772450,
  "timestamp_to": 797230,
  "duration": 24780,
  "segments": [
    [
      1,
      772750,
      773230
    ],
    [
      2,
      773290,
      773980
    ],
    [
      3,
      773980,
      774960
    ],
    [
      4,
      774960,
      777090
    ],
    [
      5,
      777090,
      777550
    ],
    [
      6,
      777550,
      778270
    ],
    [
      7,
      778270,
      779490
    ],
    [
      8,
      779490,
      779990
    ],
    [
      9,
      780050,
      781080
    ],
    [
      10,
      781080,
      782720
    ],
    [
      11,
      782720,
      783290
    ],
    [
      12,
      783290,
      784110
    ],
    [
      13,
      784110,
      785490
    ],
    [
      14,
      785490,
      786490
    ],
    [
      15,
      786490,
      787720
    ],
    [
      16,
      787720,
      788700
    ],
    [
      17,
      788700,
      789480
    ],
    [
      18,
      789480,
      791340
    ],
    [
      19,
      791340,
      791920
    ],
    [
      20,
      791920,
      792730
    ],
    [
      21,
      792730,
      794080
    ],
    [
      22,
      794080,
      795040
    ],
    [
      23,
      795040,
      795790
    ],
    [
      24,
      795790,
      797230
    ]
  ]
}