{
  "verse_key": "46:32",
  "timestamp_from": 703530,
  "timestamp_to": 724550,
  "duration": 21020,
  "segments": [
    [
      1,
      703830,
      704290
    ],
    [
      2,
      704430,
      704890
    ],
    [
      3,
      704890,
      705330
    ],
    [
      4,
      705430,
      706290
    ],
    [
      5,
      706410,
      707070
    ],
    [
      6,
      707070,
      707900
    ],
    [
      7,
      707900,
      709840
    ],
    [
      8,
      709840,
      710090
    ],
    [
      9,
      710090,
      710840
    ],
    [
      10,
      710840,
      711640
    ],
    [
      11,
      711640,
      712270
    ],
    [
      12,
      712270,
      713310
    ],
    [
      13,
      713310,
      714320
    ],
    [
      14,
      714320,
      718050
    ],
    [
      15,
      718050,
      720120
    ],
    [
      16,
      720220,
      720640
    ],
    [
      17,
      720640,
      722250
    ],
    [
      18,
      722250,
      724550
    ]
  ]
}