{
  "verse_key": "27:93",
  "timestamp_from": 1450760,
  "timestamp_to": 1467360,
  "duration": 16600,
  "segments": [
    [
      1,
      1450960,
      1451590
    ],
    [
      2,
      1451590,
      1452360
    ],
    [
      3,
      1452360,
      1453330
    ],
    [
      4,
      1453330,
      1454580
    ],
    [
      5,
      1454580,
      1456010
    ],
    [
      6,
      1456010,
      1458730
    ],
    [
      7,
      1458730,
      1459380
    ],
    [
      8,
      1459380,
      1460070
    ],
    [
      9,
      1460150,
      1461440
    ],
    [
      10,
      1461440,
      1463330
    ],
    [
      11,
      1463330,
      1467360
    ]
  ]
}