{
  "verse_key": "27:23",
  "timestamp_from": 354020,
  "timestamp_to": 368280,
  "duration": 14260,
  "segments": [
    [
      1,
      354220,
      356130
    ],
    [
      2,
      356130,
      356920
    ],
    [
      3,
      356920,
      358620
    ],
    [
      4,
      358620,
      359870
    ],
    [
      5,
      359870,
      361050
    ],
    [
      6,
      361050,
      362290
    ],
    [
      7,
      362290,
      362910
    ],
    [
      8,
      362910,
      364540
    ],
    [
      9,
      364540,
      365330
    ],
    [
      10,
      365330,
      366180
    ],
    [
      11,
      366180,
      368280
    ]
  ]
}