{
  "verse_key": "10:33",
  "timestamp_from": 820100,
  "timestamp_to": 830350,
  "duration": 10250,
  "segments": [
    [
      1,
      820000,
      820970
    ],
    [
      2,
      821050,
      821870
    ],
    [
      3,
      821870,
      822700
    ],
    [
      4,
      822700,
      823410
    ],
    [
      5,
      823490,
      823930
    ],
    [
      6,
      824010,
      824880
    ],
    [
      7,
      824880,
      825740
    ],
    [
      8,
      825740,
      827440
    ],
    [
      9,
      827440,
      827870
    ],
    [
      10,
      827870,
      830350
    ]
  ]
}