{
  "verse_key": "10:101",
  "timestamp_from": 2076570,
  "timestamp_to": 2091240,
  "duration": 14670,
  "segments": [
    [
      1,
      2076870,
      2077310
    ],
    [
      2,
      2077310,
      2078750
    ],
    [
      3,
      2078750,
      2079190
    ],
    [
      4,
      2079190,
      2079810
    ],
    [
      5,
      2079810,
      2081280
    ],
    [
      6,
      2081280,
      2082500
    ],
    [
      7,
      2082500,
      2083070
    ],
    [
      8,
      2083070,
      2083760
    ],
    [
      9,
      2083760,
      2084950
    ],
    [
      10,
      2084950,
      2086540
    ],
    [
      11,
      2086540,
      2087660
    ],
    [
      12,
      2087660,
      2088300
    ],
    [
      13,
      2088440,
      2088900
    ],
    [
      14,
      2088900,
      2091240
    ]
  ]
}