{
  "verse_key": "10:102",
  "timestamp_from": 2091360,
  "timestamp_to": 2110440,
  "duration": 19080,
  "segments": [
    [
      1,
      2091560,
      2092230
    ],
    [
      2,
      2092230,
      2094380
    ],
    [
      3,
      2094380,
      2095200
    ],
    [
      4,
      2095200,
      2095770
    ],
    [
      5,
      2095770,
      2096830
    ],
    [
      6,
      2096930,
      2097820
    ],
    [
      7,
      2097820,
      2098450
    ],
    [
      8,
      2098450,
      2099840
    ],
    [
      9,
      2099840,
      2101330
    ],
    [
      10,
      2101330,
      2101710
    ],
    [
      11,
      2101710,
      2103790
    ],
    [
      12,
      2103790,
      2105250
    ],
    [
      13,
      2105250,
      2106750
    ],
    [
      14,
      2106750,
      2107140
    ],
    [
      15,
      2107200,
      2110440
    ]
  ]
}