{
  "verse_key": "40:31",
  "timestamp_from": 546440,
  "timestamp_to": 562310,
  "duration": 15870,
  "segments": [
    [
      1,
      546640,
      547230
    ],
    [
      2,
      547230,
      547600
    ],
    [
      3,
      547600,
      548450
    ],
    [
      4,
      548450,
      549970
    ],
    [
      5,
      549970,
      551840
    ],
    [
      6,
      551840,
      552870
    ],
    [
      7,
      552870,
      554080
    ],
    [
      8,
      554080,
      555250
    ],
    [
      9,
      555250,
      557060
    ],
    [
      10,
      557060,
      557510
    ],
    [
      11,
      557610,
      558260
    ],
    [
      12,
      558260,
      559090
    ],
    [
      13,
      559090,
      559730
    ],
    [
      14,
      559850,
      562310
    ]
  ]
}