{
  "verse_key": "65:3",
  "timestamp_from": 89430,
  "timestamp_to": 108130,
  "duration": 18700,
  "segments": [
    [
      1,
      89630,
      90780
    ],
    [
      2,
      90780,
      91110
    ],
    [
      3,
      91110,
      91730
    ],
    [
      4,
      91730,
      92120
    ],
    [
      5,
      92120,
      93640
    ],
    [
      6,
      93640,
      94900
    ],
    [
      7,
      94900,
      96000
    ],
    [
      8,
      96000,
      96400
    ],
    [
      9,
      96460,
      97080
    ],
    [
      10,
      97080,
      97620
    ],
    [
      11,
      97620,
      98910
    ],
    [
      12,
      98910,
      100360
    ],
    [
      13,
      100480,
      101120
    ],
    [
      14,
      101120,
      101920
    ],
    [
      15,
      101920,
      103210
    ],
    [
      16,
      103210,
      103580
    ],
    [
      17,
      103580,
      104150
    ],
    [
      18,
      104250,
      104890
    ],
    [
      19,
      104890,
      105640
    ],
    [
      20,
      105640,
      107200
    ],
    [
      21,
      107200,
      108130
    ]
  ]
}