{
  "verse_key": "47:9",
  "timestamp_from": 135640,
  "timestamp_to": 145090,
  "duration": 9450,
  "segments": [
    [
      1,
      135940,
      136630
    ],
    [
      2,
      136710,
      138570
    ],
    [
      3,
      138570,
      139440
    ],
    [
      4,
      139440,
      139830
    ],
    [
      5,
      139830,
      141710
    ],
    [
      6,
      141830,
      142490
    ],
    [
      7,
      142490,
      143460
    ],
    [
      8,
      143460,
      145090
    ]
  ]
}