{
  "verse_key": "47:32",
  "timestamp_from": 563460,
  "timestamp_to": 591410,
  "duration": 27950,
  "segments": [
    [
      1,
      563760,
      565220
    ],
    [
      2,
      565300,
      566200
    ],
    [
      3,
      566200,
      567050
    ],
    [
      4,
      567050,
      568060
    ],
    [
      5,
      568060,
      569230
    ],
    [
      6,
      569230,
      570110
    ],
    [
      7,
      570190,
      570880
    ],
    [
      8,
      570880,
      574310
    ],
    [
      9,
      574310,
      575280
    ],
    [
      10,
      575280,
      576220
    ],
    [
      11,
      576220,
      576810
    ],
    [
      12,
      576810,
      577190
    ],
    [
      13,
      577190,
      578240
    ],
    [
      14,
      578240,
      578870
    ],
    [
      15,
      578890,
      579720
    ],
    [
      16,
      579720,
      580650
    ],
    [
      17,
      580650,
      581480
    ],
    [
      18,
      581560,
      582230
    ],
    [
      19,
      582230,
      584080
    ],
    [
      17,
      584080,
      585460
    ],
    [
      18,
      585460,
      586300
    ],
    [
      19,
      586400,
      587080
    ],
    [
      20,
      587080,
      588610
    ],
    [
      21,
      588610,
      589800
    ],
    [
      21,
      589800,
      591410
    ]
  ]
}