{
  "verse_key": "37:102",
  "timestamp_from": 714860,
  "timestamp_to": 742670,
  "duration": 27810,
  "segments": [
    [
      1,
      715060,
      716750
    ],
    [
      2,
      716750,
      717340
    ],
    [
      3,
      717340,
      717950
    ],
    [
      4,
      717950,
      718820
    ],
    [
      5,
      718820,
      719450
    ],
    [
      6,
      719450,
      719840
    ],
    [
      7,
      719840,
      720620
    ],
    [
      8,
      720620,
      722200
    ],
    [
      9,
      722200,
      722830
    ],
    [
      10,
      722830,
      723070
    ],
    [
      11,
      723070,
      724020
    ],
    [
      12,
      724020,
      725450
    ],
    [
      13,
      725450,
      726360
    ],
    [
      14,
      726440,
      727900
    ],
    [
      15,
      727900,
      728300
    ],
    [
      16,
      728300,
      730020
    ],
    [
      17,
      730020,
      730630
    ],
    [
      18,
      730630,
      731000
    ],
    [
      19,
      731000,
      731580
    ],
    [
      20,
      731580,
      732210
    ],
    [
      21,
      732210,
      732600
    ],
    [
      22,
      732600,
      733980
    ],
    [
      23,
      733980,
      735200
    ],
    [
      24,
      735200,
      736240
    ],
    [
      25,
      736240,
      738930
    ],
    [
      26,
      739030,
      739680
    ]
  ]
}