{
  "verse_key": "22:27",
  "timestamp_from": 609290,
  "timestamp_to": 625690,
  "duration": 16400,
  "segments": [
    [
      1,
      609590,
      611530
    ],
    [
      2,
      611530,
      611800
    ],
    [
      3,
      612420,
      613160
    ],
    [
      4,
      613160,
      614210
    ],
    [
      5,
      614210,
      615180
    ],
    [
      6,
      615260,
      616920
    ],
    [
      7,
      616920,
      617710
    ],
    [
      8,
      617710,
      618370
    ],
    [
      9,
      618370,
      620090
    ],
    [
      10,
      620090,
      621120
    ],
    [
      11,
      621120,
      622140
    ],
    [
      12,
      622140,
      622770
    ],
    [
      13,
      622770,
      623640
    ],
    [
      14,
      623640,
      625690
    ]
  ]
}