{
  "verse_key": "23:91",
  "timestamp_from": 1067150,
  "timestamp_to": 1092100,
  "duration": 24950,
  "segments": [
    [
      1,
      1067350,
      1067430
    ],
    [
      2,
      1067430,
      1068390
    ],
    [
      3,
      1068490,
      1069210
    ],
    [
      4,
      1069210,
      1070500
    ],
    [
      5,
      1070500,
      1071970
    ],
    [
      6,
      1071970,
      1072550
    ],
    [
      7,
      1072550,
      1073160
    ],
    [
      8,
      1073160,
      1074000
    ],
    [
      9,
      1074000,
      1074350
    ],
    [
      10,
      1074350,
      1077290
    ],
    [
      11,
      1077290,
      1077740
    ],
    [
      12,
      1077860,
      1078710
    ],
    [
      13,
      1078710,
      1079330
    ],
    [
      14,
      1079330,
      1080890
    ],
    [
      15,
      1080890,
      1081470
    ],
    [
      16,
      1081470,
      1082130
    ],
    [
      17,
      1082130,
      1083170
    ],
    [
      18,
      1083170,
      1084160
    ],
    [
      19,
      1084160,
      1084790
    ],
    [
      20,
      1084790,
      1086170
    ],
    [
      21,
      1086170,
      1087210
    ],
    [
      22,
      1087370,
      1088060
    ],
    [
      23,
      1088060,
      1089910
    ],
    [
      24,
      1089910,
      1092100
    ]
  ]
}