{
  "verse_key": "36:15",
  "timestamp_from": 153080,
  "timestamp_to": 169830,
  "duration": 16750,
  "segments": [
    [
      1,
      153280,
      154140
    ],
    [
      2,
      154140,
      154540
    ],
    [
      3,
      154540,
      156130
    ],
    [
      4,
      156130,
      156970
    ],
    [
      5,
      156970,
      158430
    ],
    [
      6,
      158430,
      159370
    ],
    [
      7,
      159370,
      159820
    ],
    [
      8,
      159920,
      161450
    ],
    [
      9,
      161490,
      162610
    ],
    [
      10,
      162610,
      163800
    ],
    [
      11,
      163800,
      164640
    ],
    [
      12,
      164640,
      165030
    ],
    [
      13,
      165030,
      166590
    ],
    [
      14,
      166590,
      167360
    ],
    [
      15,
      167360,
      169830
    ]
  ]
}