{
  "verse_key": "71:21",
  "timestamp_from": 190590,
  "timestamp_to": 203550,
  "duration": 12960,
  "segments": [
    [
      1,
      190890,
      191570
    ],
    [
      2,
      191570,
      192250
    ],
    [
      3,
      192370,
      193040
    ],
    [
      4,
      193040,
      194840
    ],
    [
      5,
      194840,
      195960
    ],
    [
      6,
      195960,
      197240
    ],
    [
      7,
      197240,
      197500
    ],
    [
      8,
      197640,
      198110
    ],
    [
      9,
      198110,
      198920
    ],
    [
      10,
      198920,
      199820
    ],
    [
      11,
      199960,
      201300
    ],
    [
      12,
      201300,
      202100
    ],
    [
      13,
      202100,
      203550
    ]
  ]
}